MANIFEST.in
README.rst
setup.py
collective/__init__.py
collective.geo.exif.egg-info/PKG-INFO
collective.geo.exif.egg-info/SOURCES.txt
collective.geo.exif.egg-info/dependency_links.txt
collective.geo.exif.egg-info/entry_points.txt
collective.geo.exif.egg-info/namespace_packages.txt
collective.geo.exif.egg-info/not-zip-safe
collective.geo.exif.egg-info/requires.txt
collective.geo.exif.egg-info/top_level.txt
collective/geo/__init__.py
collective/geo/exif/__init__.py
collective/geo/exif/configure.zcml
collective/geo/exif/interfaces.py
collective/geo/exif/readexif.py
collective/geo/exif/tests.py
collective/geo/exif/utils.py
collective/geo/exif/version.txt
collective/geo/exif/browser/__init__.py
collective/geo/exif/browser/configure.zcml
collective/geo/exif/browser/forms.py
collective/geo/exif/profiles/default/metadata.xml
docs/HISTORY.txt
docs/INSTALL.txt
docs/LICENSE.txt