Metadata-Version: 1.0
Name: collective.geo.exif
Version: 0.1
Summary: Geoannotate Images with EXIF information
Home-page: https://github.com/collective/collective.geo.exif
Author: Christian Ledermann
Author-email: christian.ledermann@gmail.com
License: GPL
Keywords: EXIF
Platform: UNKNOWN
Classifier: Framework :: Plone
Classifier: Framework :: Plone :: 4.0
Classifier: Framework :: Plone :: 4.1
Classifier: Framework :: Plone :: 4.2
Classifier: Programming Language :: Python
Classifier: Topic :: Scientific/Engineering :: GIS
Classifier: License :: OSI Approved :: GNU General Public License (GPL)
